seacrowd/__init__.py
seacrowd/config_helper.py
seacrowd/sea_datasets/__init__.py
seacrowd/sea_datasets/abui_wordnet/__init__.py
seacrowd/sea_datasets/abui_wordnet/abui_wordnet.py
seacrowd/sea_datasets/ac_iquad/__init__.py
seacrowd/sea_datasets/ac_iquad/ac_iquad.py
seacrowd/sea_datasets/alice_thi/__init__.py
seacrowd/sea_datasets/alice_thi/alice_thi.py
seacrowd/sea_datasets/alorese/__init__.py
seacrowd/sea_datasets/alorese/alorese.py
seacrowd/sea_datasets/alorese/alorese_url.py
seacrowd/sea_datasets/alt_burmese_treebank/__init__.py
seacrowd/sea_datasets/alt_burmese_treebank/alt_burmese_treebank.py
seacrowd/sea_datasets/alt_burmese_treebank/utils/__init__.py
seacrowd/sea_datasets/alt_burmese_treebank/utils/alt_burmese_treebank_utils.py
seacrowd/sea_datasets/ara_close/__init__.py
seacrowd/sea_datasets/ara_close/ara_close.py
seacrowd/sea_datasets/asr_ibsc/__init__.py
seacrowd/sea_datasets/asr_ibsc/asr_ibsc.py
seacrowd/sea_datasets/asr_indocsc/__init__.py
seacrowd/sea_datasets/asr_indocsc/asr_indocsc.py
seacrowd/sea_datasets/asr_malcsc/__init__.py
seacrowd/sea_datasets/asr_malcsc/asr_malcsc.py
seacrowd/sea_datasets/asr_sindodusc/__init__.py
seacrowd/sea_datasets/asr_sindodusc/asr_sindodusc.py
seacrowd/sea_datasets/asr_smaldusc/__init__.py
seacrowd/sea_datasets/asr_smaldusc/asr_smaldusc.py
seacrowd/sea_datasets/asr_stidusc/__init__.py
seacrowd/sea_datasets/asr_stidusc/asr_stidusc.py
seacrowd/sea_datasets/audio_keyword_spotting/__init__.py
seacrowd/sea_datasets/audio_keyword_spotting/audio_keyword_spotting.py
seacrowd/sea_datasets/aya_collection_templated/__init__.py
seacrowd/sea_datasets/aya_collection_templated/aya_collection_templated.py
seacrowd/sea_datasets/aya_collection_translated/__init__.py
seacrowd/sea_datasets/aya_collection_translated/aya_collection_translated.py
seacrowd/sea_datasets/aya_dataset/__init__.py
seacrowd/sea_datasets/aya_dataset/aya_dataset.py
seacrowd/sea_datasets/aya_evaluation_suite/__init__.py
seacrowd-0.2.2.dist-info/LICENSE
seacrowd-0.2.2.dist-info/METADATA
seacrowd-0.2.2.dist-info/WHEEL
seacrowd-0.2.2.dist-info/top_level.txt
seacrowd-0.2.2.dist-info/RECORD
